<?xml version="1.0" encoding="UTF-8" ?>
<!DOCTYPE JuffScheme>
<JuffScheme>
<scheme name="HTML">
	<style name="tag" color="#45c6d6" italic="true" />
	<style name="attribute" color="#d6cf9a" />
	<style name="comment" color="#a8abb0" italic="true" />
	<style name="value" color="#d69545" />
	<style name="entity" color="#8a602c" />
	<style name="singleString" color="#d69545" />
	<style name="doubleString" color="#d69545" />
	<!-- JavaScript -->
	<style name="jsComment" color="#a8abb0" italic="true" />
	<style name="jsNumber" color="#8a602c" />
	<style name="jsWord" color="#d6cf9a" />
	<style name="jsKeyword" color="#45c6d6" italic="true" />
	<style name="jsSingleString" color="#d69545" />
	<style name="jsDoubleString" color="#d69545" />
	<style name="jsSymbol" color="#d6cf9a" />
</scheme>
</JuffScheme>
